cybernetics/__init__.py
cybernetics/controls/__init__.py
cybernetics/controls/piecewise_constant_controller.py
cybernetics/controls/piecewise_linear_controller.py
cybernetics/real/__init__.py
cybernetics/real/satellite_stabilization.py
cybernetics-0.1.2.dist-info/DESCRIPTION.rst
cybernetics-0.1.2.dist-info/METADATA
cybernetics-0.1.2.dist-info/RECORD
cybernetics-0.1.2.dist-info/WHEEL
cybernetics-0.1.2.dist-info/metadata.json
cybernetics-0.1.2.dist-info/top_level.txt
