Metadata-Version: 2.0
Name: cybernetics
Version: 0.1.2
Summary: Cybernetics - package with various dynamic models and cybernetics tools
Home-page: https://github.com/wol4aravio/Cybernetics
Author: Panovskiy Valentin
Author-email: panovskiy.v@yandex.ru
License: MIT License
Platform: UNKNOWN
Classifier: Intended Audience :: Education
Classifier: Intended Audience :: Science/Research
Classifier: Topic :: Scientific/Engineering :: Mathematics
Classifier: License :: OSI Approved :: MIT License
Classifier: Programming Language :: Python :: 3.6
Requires-Dist: intervallum
Requires-Dist: numpy
Requires-Dist: scipy
